qceltis/__init__.py
qceltis/main.py
qceltis/mod/__init__.py
qceltis/mod/general_functions.py
qceltis/mod/idbased_metrics.py
qceltis/mod/mzml_extract.py
qceltis/templates/report_template.html
qceltis-0.1.2.dist-info/LICENSE.txt
qceltis-0.1.2.dist-info/METADATA
qceltis-0.1.2.dist-info/WHEEL
qceltis-0.1.2.dist-info/entry_points.txt
qceltis-0.1.2.dist-info/top_level.txt
qceltis-0.1.2.dist-info/RECORD
