Metadata-Version: 2.1
Name: qceltis
Version: 0.1.2
Summary: Quality Control Package for DIA Proteomics
Home-page: https://github.com/csmc-vaneykjlab/QCeltis
Author: Manasa Vegesna
Author-email: vmanasa1129@gmail.com
Classifier: Development Status :: 3 - Alpha
Classifier: Intended Audience :: Science/Research
Classifier: Topic :: Scientific/Engineering :: Bio-Informatics
Classifier: License :: OSI Approved :: MIT License
Classifier: Programming Language :: Python :: 3.9
Requires-Python: >=3.9
License-File: LICENSE.txt
Requires-Dist: pandas ==2.0.1
Requires-Dist: numpy >=1.24.3
Requires-Dist: xlsxwriter >=3.2.0
Requires-Dist: plotly >=5.13.0
Requires-Dist: jinja2 >=3.1.3
Requires-Dist: scipy >=1.10.1
Requires-Dist: scikit-learn >=1.2.2
Requires-Dist: pymzml >=2.5.9
